fireflow/__init__.py
fireflow/__main__.py
fireflow/_remote_path.py
fireflow/_sql_parse.py
fireflow/cli.py
fireflow/object_store.py
fireflow/orm.py
fireflow/process.py
fireflow/storage.py
fireflow-0.0.1.dist-info/entry_points.txt
fireflow-0.0.1.dist-info/LICENSE
fireflow-0.0.1.dist-info/WHEEL
fireflow-0.0.1.dist-info/METADATA
fireflow-0.0.1.dist-info/RECORD
