Metadata-Version: 2.1
Name: fireflow
Version: 0.0.1
Summary: A simple async workflow engine for interfacing with FirecREST.
Author-email: Chris Sewell <chrisj_sewell@hotmail.com>
Requires-Python: >=3.8
Classifier: Operating System :: OS Independent
Classifier: Programming Language :: Python :: 3
Classifier: License :: OSI Approved :: MIT License
Requires-Dist: pyfirecrest~=1.3.0
Requires-Dist: aiohttp~=3.8
Requires-Dist: sqlalchemy~=2.0
Requires-Dist: jinja2
Requires-Dist: pyyaml
Requires-Dist: virtual-glob
Requires-Dist: typer[all]~=0.7.0 ; extra == "cli"
Requires-Dist: pyparsing ; extra == "cli"
Requires-Dist: pytest ; extra == "testing"
Project-URL: Home, https://github.com/chrisjsewell/fireflow
Provides-Extra: cli
Provides-Extra: testing
